kumo_rfm_mcp/__init__.py
kumo_rfm_mcp/_version.py
kumo_rfm_mcp/config.py
kumo_rfm_mcp/server.py
kumo_rfm_mcp/session.py
kumo_rfm_mcp/resources/graph-setup.md
kumo_rfm_mcp/resources/overview.md
kumo_rfm_mcp/resources/predictive-query.md
kumo_rfm_mcp/tools/__init__.py
kumo_rfm_mcp/tools/auth.py
kumo_rfm_mcp/tools/docs.py
kumo_rfm_mcp/tools/graph.py
kumo_rfm_mcp/tools/io.py
kumo_rfm_mcp/tools/model.py
kumo_rfm_mcp-0.2.1.dist-info/METADATA
kumo_rfm_mcp-0.2.1.dist-info/WHEEL
kumo_rfm_mcp-0.2.1.dist-info/entry_points.txt
kumo_rfm_mcp-0.2.1.dist-info/licenses/LICENSE
kumo_rfm_mcp-0.2.1.dist-info/RECORD
