Metadata-Version: 2.4
Name: kumo-rfm-mcp
Version: 0.2.1
Summary: Model Context Protocol server for KumoRFM
Project-URL: Homepage, https://kumorfm.ai
Project-URL: Repository, https://github.com/kumo-ai/kumo-rfm-mcp.git
Project-URL: Issues, https://github.com/kumo-ai/kumo-rfm-mcp/issues
Author-email: "Kumo.AI" <hello@kumo.ai>
License: MIT
License-File: LICENSE
Keywords: foundation model,kumo,mcp,relational data,rfm
Classifier: Development Status :: 3 - Alpha
Classifier: Environment :: Console
Classifier: Intended Audience :: Developers
Classifier: License :: OSI Approved :: MIT License
Classifier: Operating System :: OS Independent
Classifier: Programming Language :: Python :: 3
Classifier: Programming Language :: Python :: 3.10
Classifier: Programming Language :: Python :: 3.11
Classifier: Programming Language :: Python :: 3.12
Classifier: Programming Language :: Python :: 3.13
Classifier: Topic :: Scientific/Engineering :: Artificial Intelligence
Classifier: Topic :: Scientific/Engineering :: Information Analysis
Classifier: Topic :: Software Development :: Libraries :: Python Modules
Requires-Python: >=3.10
Requires-Dist: fastmcp<3,>=2.2.7
Requires-Dist: kumoai==2.8.0
Provides-Extra: dev
Requires-Dist: pytest; extra == 'dev'
Requires-Dist: pytest-asyncio; extra == 'dev'
